MANIFEST.in
README.md
setup.py
buzzard/__init__.py
buzzard/_a_async_raster.py
buzzard/_a_emissary.py
buzzard/_a_emissary_raster.py
buzzard/_a_emissary_vector.py
buzzard/_a_gdal_raster.py
buzzard/_a_gdal_vector.py
buzzard/_a_pooled_emissary.py
buzzard/_a_pooled_emissary_raster.py
buzzard/_a_pooled_emissary_vector.py
buzzard/_a_raster_recipe.py
buzzard/_a_source.py
buzzard/_a_source_raster.py
buzzard/_a_source_raster_remap.py
buzzard/_a_source_vector.py
buzzard/_a_stored.py
buzzard/_a_stored_raster.py
buzzard/_a_stored_vector.py
buzzard/_cached_raster_recipe.py
buzzard/_dataset.py
buzzard/_dataset_back.py
buzzard/_dataset_back_activation_pool.py
buzzard/_dataset_back_conversions.py
buzzard/_dataset_back_scheduler.py
buzzard/_dataset_pools_container.py
buzzard/_dataset_register.py
buzzard/_debug_observers_manager.py
buzzard/_env.py
buzzard/_footprint.py
buzzard/_footprint_intersection.py
buzzard/_footprint_move.py
buzzard/_footprint_tile.py
buzzard/_gdal_file_raster.py
buzzard/_gdal_file_vector.py
buzzard/_gdal_mem_raster.py
buzzard/_gdal_memory_vector.py
buzzard/_numpy_raster.py
buzzard/_pint_interop.py
buzzard.egg-info/PKG-INFO
buzzard.egg-info/SOURCES.txt
buzzard.egg-info/dependency_links.txt
buzzard.egg-info/requires.txt
buzzard.egg-info/top_level.txt
buzzard/_actors/__init__.py
buzzard/_actors/computation_accumulator.py
buzzard/_actors/computation_gate1.py
buzzard/_actors/computation_gate2.py
buzzard/_actors/computer.py
buzzard/_actors/global_priorities_watcher.py
buzzard/_actors/message.py
buzzard/_actors/pool_job.py
buzzard/_actors/pool_waiting_room.py
buzzard/_actors/pool_working_room.py
buzzard/_actors/priorities.py
buzzard/_actors/production_gate.py
buzzard/_actors/resampler.py
buzzard/_actors/top_level.py
buzzard/_actors/cached/__init__.py
buzzard/_actors/cached/cache_extractor.py
buzzard/_actors/cached/cache_supervisor.py
buzzard/_actors/cached/file_checker.py
buzzard/_actors/cached/merger.py
buzzard/_actors/cached/producer.py
buzzard/_actors/cached/queries_handler.py
buzzard/_actors/cached/query_infos.py
buzzard/_actors/cached/reader.py
buzzard/_actors/cached/writer.py
buzzard/_tools/__init__.py
