Metadata-Version: 2.1
Name: buzzard
Version: 0.6.5
Summary: GIS files manipulations
Home-page: https://github.com/earthcube-lab/buzzard
Author: ngoguey
Author-email: ngoguey@student.42.fr
Maintainer: ngoguey
Maintainer-email: ngoguey@student.42.fr
License: Apache License 2.0
Download-URL: https://github.com/earthcube-lab/buzzard/archive/0.6.5.tar.gz
Keywords: gdal gis raster shp dxf tif vector
Platform: UNKNOWN
Classifier: Development Status :: 4 - Beta
Classifier: Intended Audience :: Developers
Classifier: Intended Audience :: Information Technology
Classifier: Intended Audience :: Science/Research
Classifier: License :: OSI Approved :: Apache Software License
Classifier: Operating System :: OS Independent
Classifier: Programming Language :: Python :: 3
Classifier: Programming Language :: Python :: 3.4
Classifier: Programming Language :: Python :: 3.5
Classifier: Programming Language :: Python :: 3.6
Classifier: Programming Language :: Python :: 3.7
Classifier: Topic :: Scientific/Engineering :: GIS
Requires-Python: >=3.4
